<?xml version="1.0" encoding="utf-8"?>
<openerp>
    <data>
        <record id="view_event_form_inh_pa_code" model="ir.ui.view" >
            <field name="name">view.event.form.inh.pa.codec</field>
            <field name="model">event.event</field>
            <field name="inherit_id" ref="event_sale.view_event_form"/>
            <field name="arch" type="xml">
                <page string="Badge" position="attributes">
                    <attribute name="invisible">1</attribute>
                </page>
                <xpath expr="//tree[@string='Payments']//field[@name='product_id']" position="after">
                    <field name="pa_partner" />
                </xpath>
                <field name="event_ticket_ids" position="before">
                    <group colspan="4" col="8">
                        <button name="button_duplicate_ticket" type="object" 
                                string="Duplicate line" colspan="8"/>
                    </group>
                </field>
            </field>
        </record>
    </data>
</openerp>
